{"_ts":[1489327420],"_r":{"breakdown":{"html":{"bytes":[47189],"requests":[10]},"js":{"bytes":[408716],"requests":[28]},"css":{"bytes":[38622],"requests":[2]},"image":{"bytes":[658653],"requests":[52]},"flash":{"bytes":[0],"requests":[0]},"font":{"bytes":[46634],"requests":[2]},"other":{"bytes":[1584],"requests":[1]}},"date":[1489327420],"domElements":[2242],"domInteractive":[3329],"firstPaint":[2415],"fullyLoaded":[8824],"id":["170312_ME_NYE"],"loadTime":[6320],"render":[2581],"SpeedIndex":[3302],"TTFB":[329],"videoFrames":[[{"_t":0,"_vc":0},{"_t":2600,"_vc":66},{"_t":3100,"_vc":68},{"_t":3200,"_vc":68},{"_t":3400,"_vc":68},{"_t":4300,"_vc":83},{"_t":4700,"_vc":84},{"_t":5200,"_vc":100}]],"visualComplete":[5200]}}